{
    "key": "group_6486035fef0f6",
    "title": "Background",
    "fields": [
        {
            "key": "field_648603608837c",
            "label": "Background Content",
            "name": "content",
            "aria-label": "",
            "type": "radio",
            "instructions": "Set background color in the Block style tab",
            "required": 0,
            "conditional_logic": 0,
            "wrapper": {
                "width": "",
                "class": "",
                "id": ""
            },
            "choices": {
                "none": "None",
                "color": "Color",
                "image": "Image",
                "video": "Video"
            },
            "default_value": "none : None",
            "return_format": "value",
            "allow_null": 0,
            "other_choice": 0,
            "layout": "horizontal",
            "save_other_choice": 0
        },
        {
            "key": "field_648603608bdfe",
            "label": "Video URL (mp4)",
            "name": "video",
            "aria-label": "",
            "type": "file",
            "instructions": "Please upload fallback image as well.",
            "required": 0,
            "conditional_logic": [
                [
                    {
                        "field": "field_648603608837c",
                        "operator": "==",
                        "value": "video"
                    }
                ]
            ],
            "wrapper": {
                "width": "",
                "class": "",
                "id": ""
            },
            "uploader": "wp",
            "return_format": "url",
            "library": "all",
            "min_size": "",
            "max_size": "",
            "mime_types": "mp4"
        },
        {
            "key": "field_648603608f8a4",
            "label": "Image Upload",
            "name": "image",
            "aria-label": "",
            "type": "file",
            "instructions": "Also used as video fallback",
            "required": 0,
            "conditional_logic": [
                [
                    {
                        "field": "field_648603608837c",
                        "operator": "==",
                        "value": "image"
                    },
                    {
                        "field": "field_64a59c2fc9708",
                        "operator": "==",
                        "value": "upload"
                    }
                ],
                [
                    {
                        "field": "field_648603608837c",
                        "operator": "==",
                        "value": "video"
                    },
                    {
                        "field": "field_64a59c2fc9708",
                        "operator": "==",
                        "value": "upload"
                    }
                ]
            ],
            "wrapper": {
                "width": "50",
                "class": "",
                "id": ""
            },
            "uploader": "wp",
            "return_format": "id",
            "library": "all",
            "min_size": "",
            "max_size": "",
            "mime_types": ""
        },
        {
            "key": "field_65e8f7c5f2703",
            "label": "Image Upload Mobile",
            "name": "image_upload_mobile",
            "aria-label": "",
            "type": "file",
            "instructions": "Also used as video fallback",
            "required": 0,
            "conditional_logic": [
                [
                    {
                        "field": "field_648603608837c",
                        "operator": "==",
                        "value": "image"
                    },
                    {
                        "field": "field_64a59c2fc9708",
                        "operator": "==",
                        "value": "upload"
                    }
                ],
                [
                    {
                        "field": "field_648603608837c",
                        "operator": "==",
                        "value": "video"
                    },
                    {
                        "field": "field_64a59c2fc9708",
                        "operator": "==",
                        "value": "upload"
                    }
                ]
            ],
            "wrapper": {
                "width": "50",
                "class": "",
                "id": ""
            },
            "uploader": "wp",
            "return_format": "id",
            "library": "all",
            "min_size": "",
            "max_size": "",
            "mime_types": ""
        },
        {
            "key": "field_65e1038d99950",
            "label": "Background Image Size",
            "name": "background_image_size",
            "aria-label": "",
            "type": "select",
            "instructions": "",
            "required": 0,
            "conditional_logic": [
                [
                    {
                        "field": "field_648603608837c",
                        "operator": "==",
                        "value": "image"
                    }
                ],
                [
                    {
                        "field": "field_648603608837c",
                        "operator": "==",
                        "value": "video"
                    }
                ]
            ],
            "wrapper": {
                "width": "34",
                "class": "",
                "id": ""
            },
            "choices": {
                "full": "full",
                "1536x1536": "1536x1536",
                "large": "Large 1024x1024",
                "medium_large": "Medium Large 768x0",
                "medium": "Medium 300x200",
                "thumbnail": "Thumbnail 150 x 150"
            },
            "default_value": "1536x1536",
            "return_format": "value",
            "multiple": 0,
            "allow_null": 0,
            "ui": 0,
            "ajax": 0,
            "placeholder": "",
            "allow_custom": 0,
            "search_placeholder": ""
        },
        {
            "key": "field_64a59c2fc9708",
            "label": "Background Image Source",
            "name": "background_image_source",
            "aria-label": "",
            "type": "select",
            "instructions": "",
            "required": 0,
            "conditional_logic": [
                [
                    {
                        "field": "field_648603608837c",
                        "operator": "==",
                        "value": "image"
                    }
                ],
                [
                    {
                        "field": "field_648603608837c",
                        "operator": "==",
                        "value": "video"
                    }
                ]
            ],
            "wrapper": {
                "width": "33",
                "class": "",
                "id": ""
            },
            "choices": {
                "upload": "Upload",
                "featured": "Featured Image"
            },
            "default_value": "upload",
            "return_format": "value",
            "multiple": 0,
            "allow_null": 0,
            "ui": 0,
            "ajax": 0,
            "placeholder": "",
            "allow_custom": 0,
            "search_placeholder": ""
        },
        {
            "key": "field_65e106abafec2",
            "label": "Background Image Format",
            "name": "background_image_format",
            "aria-label": "",
            "type": "select",
            "instructions": "",
            "required": 0,
            "conditional_logic": [
                [
                    {
                        "field": "field_648603608837c",
                        "operator": "==",
                        "value": "image"
                    }
                ],
                [
                    {
                        "field": "field_648603608837c",
                        "operator": "==",
                        "value": "video"
                    }
                ]
            ],
            "wrapper": {
                "width": "33",
                "class": "",
                "id": ""
            },
            "choices": {
                "optimized": "optimized",
                "inherit": "inherit"
            },
            "default_value": "optimized",
            "return_format": "value",
            "multiple": 0,
            "allow_null": 0,
            "ui": 0,
            "ajax": 0,
            "placeholder": "",
            "allow_custom": 0,
            "search_placeholder": ""
        },
        {
            "key": "field_64860360a60f2",
            "label": "Background Size",
            "name": "size",
            "aria-label": "",
            "type": "select",
            "instructions": "",
            "required": 0,
            "conditional_logic": [
                [
                    {
                        "field": "field_648603608837c",
                        "operator": "==",
                        "value": "image"
                    }
                ],
                [
                    {
                        "field": "field_648603608837c",
                        "operator": "==",
                        "value": "video"
                    }
                ]
            ],
            "wrapper": {
                "width": "34",
                "class": "",
                "id": ""
            },
            "choices": {
                "cover": "Cover",
                "contain": "Contain",
                "auto": "Auto"
            },
            "default_value": "cover",
            "return_format": "value",
            "multiple": 0,
            "allow_null": 0,
            "ui": 0,
            "ajax": 0,
            "placeholder": "",
            "allow_custom": 0,
            "search_placeholder": ""
        },
        {
            "key": "field_64860360a9d00",
            "label": "Background Position",
            "name": "position",
            "aria-label": "",
            "type": "select",
            "instructions": "",
            "required": 0,
            "conditional_logic": [
                [
                    {
                        "field": "field_648603608837c",
                        "operator": "==",
                        "value": "image"
                    }
                ],
                [
                    {
                        "field": "field_648603608837c",
                        "operator": "==",
                        "value": "video"
                    }
                ]
            ],
            "wrapper": {
                "width": "33",
                "class": "",
                "id": ""
            },
            "choices": {
                "center center": "Center Center",
                "center left": "Center Left",
                "center right": "Center Right",
                "top center": "Top Center",
                "top left": "Top Left",
                "top right": "Top Right",
                "bottom center": "Bottom Center",
                "bottom left": "Bottom Left",
                "bottom right": "Bottom Right"
            },
            "default_value": "center center",
            "return_format": "value",
            "multiple": 0,
            "allow_null": 0,
            "ui": 0,
            "ajax": 0,
            "placeholder": "",
            "allow_custom": 0,
            "search_placeholder": ""
        },
        {
            "key": "field_64860360ad797",
            "label": "Background Repeat",
            "name": "repeat",
            "aria-label": "",
            "type": "select",
            "instructions": "",
            "required": 0,
            "conditional_logic": [
                [
                    {
                        "field": "field_648603608837c",
                        "operator": "==",
                        "value": "video"
                    }
                ],
                [
                    {
                        "field": "field_648603608837c",
                        "operator": "==",
                        "value": "image"
                    }
                ]
            ],
            "wrapper": {
                "width": "33",
                "class": "",
                "id": ""
            },
            "choices": {
                "no-repeat": "no-repeat",
                "repeat": "repeat"
            },
            "default_value": "no-repeat",
            "return_format": "value",
            "multiple": 0,
            "allow_null": 0,
            "ui": 0,
            "ajax": 0,
            "placeholder": "",
            "allow_custom": 0,
            "search_placeholder": ""
        },
        {
            "key": "field_65e8ebdd71512",
            "label": "Background Size Mobile",
            "name": "background_size_mobile",
            "aria-label": "",
            "type": "select",
            "instructions": "",
            "required": 0,
            "conditional_logic": [
                [
                    {
                        "field": "field_648603608837c",
                        "operator": "==",
                        "value": "image"
                    }
                ],
                [
                    {
                        "field": "field_648603608837c",
                        "operator": "==",
                        "value": "video"
                    }
                ]
            ],
            "wrapper": {
                "width": "34",
                "class": "",
                "id": ""
            },
            "choices": {
                "default": "default",
                "cover": "Cover",
                "contain": "Contain",
                "auto": "Auto"
            },
            "default_value": "default",
            "return_format": "value",
            "multiple": 0,
            "allow_null": 0,
            "ui": 0,
            "ajax": 0,
            "placeholder": "",
            "allow_custom": 0,
            "search_placeholder": ""
        },
        {
            "key": "field_65e8ebe771513",
            "label": "Background Position Mobile",
            "name": "background_position_mobile",
            "aria-label": "",
            "type": "select",
            "instructions": "",
            "required": 0,
            "conditional_logic": [
                [
                    {
                        "field": "field_648603608837c",
                        "operator": "==",
                        "value": "image"
                    }
                ],
                [
                    {
                        "field": "field_648603608837c",
                        "operator": "==",
                        "value": "video"
                    }
                ]
            ],
            "wrapper": {
                "width": "33",
                "class": "",
                "id": ""
            },
            "choices": {
                "default": "default",
                "center-center": "Center Center",
                "center-left": "Center Left",
                "center-right": "Center Right",
                "top-center": "Top Center",
                "top-left": "Top Left",
                "top-right": "Top Right",
                "bottom-center": "Bottom Center",
                "bottom-left": "Bottom Left",
                "bottom-right": "Bottom Right"
            },
            "default_value": "default",
            "return_format": "value",
            "multiple": 0,
            "allow_null": 0,
            "ui": 0,
            "ajax": 0,
            "placeholder": "",
            "allow_custom": 0,
            "search_placeholder": ""
        },
        {
            "key": "field_65e8ec68236f5",
            "label": "Overlay Visibility",
            "name": "overlay_visibility",
            "aria-label": "",
            "type": "select",
            "instructions": "",
            "required": 0,
            "conditional_logic": [
                [
                    {
                        "field": "field_648603608837c",
                        "operator": "==",
                        "value": "image"
                    }
                ],
                [
                    {
                        "field": "field_648603608837c",
                        "operator": "==",
                        "value": "video"
                    }
                ]
            ],
            "wrapper": {
                "width": "33",
                "class": "",
                "id": ""
            },
            "choices": {
                "default": "default",
                "desktop": "desktop",
                "mobile": "mobile"
            },
            "default_value": "default",
            "return_format": "value",
            "multiple": 0,
            "allow_null": 0,
            "ui": 0,
            "ajax": 0,
            "placeholder": "",
            "allow_custom": 0,
            "search_placeholder": ""
        },
        {
            "key": "field_648603609333d",
            "label": "Background Color",
            "name": "color",
            "aria-label": "",
            "type": "clone",
            "instructions": "Also used as overlay if image or video background is selected",
            "required": 0,
            "conditional_logic": [
                [
                    {
                        "field": "field_648603608837c",
                        "operator": "==",
                        "value": "color"
                    }
                ],
                [
                    {
                        "field": "field_648603608837c",
                        "operator": "==",
                        "value": "image"
                    }
                ],
                [
                    {
                        "field": "field_648603608837c",
                        "operator": "==",
                        "value": "video"
                    }
                ]
            ],
            "wrapper": {
                "width": "",
                "class": "label-hide",
                "id": ""
            },
            "clone": [
                "group_646f908576c59"
            ],
            "display": "group",
            "layout": "block",
            "prefix_label": 0,
            "prefix_name": 0,
            "acfe_seamless_style": 1,
            "acfe_clone_modal": 0,
            "acfe_clone_modal_close": 0,
            "acfe_clone_modal_button": "",
            "acfe_clone_modal_size": "large"
        },
        {
            "key": "field_66709c7abd375",
            "label": "Background Gradient",
            "name": "background_gradient",
            "aria-label": "",
            "type": "textarea",
            "instructions": "Format: <br>\r\nlinear-gradient(0deg, rgba(130, 36, 227, 0.5), rgba(130, 36, 227, 0.5))<br>\r\nOverrides background image color",
            "required": 0,
            "conditional_logic": [
                [
                    {
                        "field": "field_648603608837c",
                        "operator": "==",
                        "value": "color"
                    }
                ],
                [
                    {
                        "field": "field_648603608837c",
                        "operator": "==",
                        "value": "image"
                    }
                ],
                [
                    {
                        "field": "field_648603608837c",
                        "operator": "==",
                        "value": "video"
                    }
                ]
            ],
            "wrapper": {
                "width": "",
                "class": "",
                "id": ""
            },
            "default_value": "",
            "acfe_textarea_code": 1,
            "maxlength": "",
            "rows": 4,
            "placeholder": "",
            "new_lines": ""
        }
    ],
    "location": [
        [
            {
                "param": "post_type",
                "operator": "==",
                "value": "post"
            }
        ]
    ],
    "menu_order": 0,
    "position": "normal",
    "style": "default",
    "label_placement": "left",
    "instruction_placement": "label",
    "hide_on_screen": "",
    "active": false,
    "description": "",
    "show_in_rest": 0,
    "acfe_display_title": "",
    "acfe_autosync": [
        "json"
    ],
    "acfe_form": 0,
    "acfe_meta": "",
    "acfe_note": "",
    "modified": 1718662508,
    "acfe_categories": {
        "global-functions": "Global Functions"
    }
}
